[
  {
    "name": "Add",
    "type": "icon",
    "definition": {
      "icon": "add_circle",
      "style": {
        "backgroundColor": "#dba2a2"
      },
      "portStyle": {
        "--port-color": "white",
        "--hover-color": "red"
      },
      "iconStyle": {
        "color": "black"
      },
      "inputs": [
        { "name": "in1", "label": "" },
        { "name": "in2", "label": "" }
      ],
      "outputs": [
        {
          "name": "out1",
          "label": ""
        }
      ]
    }
  }
]
